LICENSE
MANIFEST.in
README.rst
setup.py
fedmsg_middleware/__init__.py
fedmsg_middleware/middleware.py
fedmsg_middleware.egg-info/PKG-INFO
fedmsg_middleware.egg-info/SOURCES.txt
fedmsg_middleware.egg-info/dependency_links.txt
fedmsg_middleware.egg-info/entry_points.txt
fedmsg_middleware.egg-info/not-zip-safe
fedmsg_middleware.egg-info/requires.txt
fedmsg_middleware.egg-info/top_level.txt