Metadata-Version: 1.1
Name: fedmsg-middleware
Version: 0.0.3
Summary: WSGI middleware for display fedmsg messages.
Home-page: http://github.com/ralphbean/fedmsg_middleware
Author: Ralph Bean
Author-email: rbean@redhat.com
License: LGPLv2+
Platform: UNKNOWN
Classifier: Development Status :: 4 - Beta
Classifier: Topic :: Internet :: WWW/HTTP :: WSGI :: Middleware
Classifier: Intended Audience :: Developers
Classifier: License :: OSI Approved :: MIT License
